pyosudb/__init__.py
pyosudb/collectiondb.py
pyosudb/datatypes.py
pyosudb/osudb.py
pyosudb/presencedb.py
pyosudb/scoresdb.py
pyosudb/utils.py
pyosudb-0.1.1.dist-info/LICENSE
pyosudb-0.1.1.dist-info/METADATA
pyosudb-0.1.1.dist-info/WHEEL
pyosudb-0.1.1.dist-info/top_level.txt
pyosudb-0.1.1.dist-info/RECORD
