Metadata-Version: 2.1
Name: pyosudb
Version: 0.1.1
Summary: Parsing osu! database files
Author-email: OlegSuperBro <olegrakovic323@gmail.com>
Project-URL: Homepage, https://github.com/OlegSuperBro/pyosudb
Project-URL: Bug Tracker, https://github.com/OlegSuperBro/pyosudb/issues
Classifier: Programming Language :: Python :: 3
Classifier: License :: OSI Approved :: MIT License
Classifier: Operating System :: OS Independent
Requires-Python: >=3.7
License-File: LICENSE
